ipyfacets/__init__.py
ipyfacets-0.3.0.dist-info/LICENSE
ipyfacets-0.3.0.dist-info/WHEEL
ipyfacets-0.3.0.dist-info/METADATA
ipyfacets-0.3.0.dist-info/RECORD
